lgca/__init__.py
lgca/settings.py
lgca/automata/__init__.py
lgca/automata/fhp_i.py
lgca/automata/fhp_ii.py
lgca/automata/fhp_iii.py
lgca/automata/hpp.py
lgca/automata/lbm.py
lgca/automata/lgca.py
lgca/config/collisions.yaml
lgca/config/colors.json
lgca/config/fhp_i.yaml
lgca/config/fhp_ii.yaml
lgca/config/fhp_iii.yaml
lgca/config/hpp.yaml
lgca/data/patterns/fhp/collision.json
lgca/data/patterns/fhp/simple-pointy.json
lgca/data/patterns/fhp/wiki.json
lgca/data/patterns/hpp/collision.json
lgca/data/patterns/hpp/hahm.json
lgca/data/patterns/hpp/quintana.json
lgca/data/patterns/hpp/simple.json
lgca/data/patterns/hpp/simul.json
lgca/data/patterns/hpp/wall.json
lgca/data/patterns/hpp/wiki-hpp-simulation.json
lgca/data/patterns/hpp/wiki.json
lgca/data/patterns/lbm/obstacle.json
lgca/display/__init__.py
lgca/display/base_grid.py
lgca/display/hexagonal_grid.py
lgca/display/square_grid.py
lgca/display/triangular_grid.py
lgca/entrypoints/gen.py
lgca/entrypoints/gui.py
lgca/utils/add_shape.py
lgca/utils/common.py
lgca/utils/config_loader.py
lgca/utils/table_generator.py
lgca/vendor/hexagons.py
lgca-0.4.1.dist-info/LICENSE
lgca-0.4.1.dist-info/METADATA
lgca-0.4.1.dist-info/WHEEL
lgca-0.4.1.dist-info/entry_points.txt
lgca-0.4.1.dist-info/top_level.txt
lgca-0.4.1.dist-info/RECORD
