Metadata-Version: 2.1
Name: lgca
Version: 0.4.1
Summary: Lattice gas automata implemented in Python.
Author-email: Jacek Siciarek <siciarek@gmail.com>
Maintainer-email: Jacek Siciarek <siciarek@gmail.com>
License:                     GNU GENERAL PUBLIC LICENSE
Project-URL: Homepage, https://github.com/siciarek/lgca
Project-URL: Documentation, https://github.com/siciarek/lgca/tree/master/docs
Project-URL: Repository, https://github.com/siciarek/lgca
Project-URL: Changelog, https://github.com/siciarek/lgca/blob/master/docs/changelog.md
Classifier: Development Status :: 4 - Beta
Classifier: Programming Language :: Python :: 3.9
Classifier: Programming Language :: Python :: 3.10
Classifier: Programming Language :: Python :: 3.11
Classifier: Programming Language :: Python :: 3.12
Requires-Python: <3.13,>=3.9
License-File: LICENSE
Requires-Dist: pygame~=2.5.2
Requires-Dist: pyaml~=24.12.1
Requires-Dist: mypy~=1.14.0
Requires-Dist: click~=8.1.7
Requires-Dist: pillow~=11.0.0
Requires-Dist: ffmpy~=0.5.0
Requires-Dist: numpy==2.2.1
Provides-Extra: doc
Requires-Dist: git-changelog~=2.5.3; extra == "doc"
Requires-Dist: mkdocs~=1.5.3; extra == "doc"
Requires-Dist: mkdocs-material~=9.5.17; extra == "doc"
Requires-Dist: mkdocs-material-extensions~=1.3.1; extra == "doc"
Requires-Dist: numpy~=2.2.1; extra == "doc"
Requires-Dist: pip-tools~=7.4.1; extra == "doc"
Provides-Extra: test
Requires-Dist: pytest~=8.3.4; extra == "test"
Requires-Dist: pytest-xdist~=3.5.0; extra == "test"
Requires-Dist: pytest-cov~=6.0.0; extra == "test"
Requires-Dist: pytest-mock~=3.12.0; extra == "test"
Requires-Dist: tox~=4.14.2; extra == "test"
Provides-Extra: analysis
Requires-Dist: radon~=6.0.1; extra == "analysis"
Requires-Dist: ruff~=0.3.4; extra == "analysis"
Requires-Dist: pre_commit~=3.6.2; extra == "analysis"
Requires-Dist: bandit[toml]~=1.7.8; extra == "analysis"
Requires-Dist: licensecheck~=2024.2; extra == "analysis"
Provides-Extra: dev
Requires-Dist: lgca[test]; extra == "dev"
Requires-Dist: lgca[analysis]; extra == "dev"
Requires-Dist: lgca[doc]; extra == "dev"
